[
{
"type":"motivation",
"motivation":"vengeance",
"require":[{"type":"character","faction":"evil"}],
"description":"item0 has killed my list0",
"list0":["mother","father","parents","brother","sister"]
},
{
"type":"start",
"require":[{"type":"character","faction":"evil"}],
"description":"item0 has killed my list0",
"list0":["mother","father","parents","brother","sister"]
},
{
"type":"destroy",
"target":[{"type":"character","faction":"evil"}],
"followUp":"talk"
},
{
"type":"talk",
"target":[{"type":"character"}]
},
{
"type":"give",
"target":[{"type":"item","target":"character"}]
},
{
"type":"defend",
"target":[{"type":"character"}]
},
{
"type":"visit",
"target":[{"type":"area"}]
},
{
"type":"get",
"target":[{"type":"item"}]
}
]
